pkgstats/__init__.py
pkgstats/model.py
pkgstats/parse.py
pkgstats/pkgstats.py
pkgstats/popcon.py
pkgstats-0.1.0.dist-info/METADATA
pkgstats-0.1.0.dist-info/WHEEL
pkgstats-0.1.0.dist-info/entry_points.txt
pkgstats-0.1.0.dist-info/top_level.txt
pkgstats-0.1.0.dist-info/RECORD
