Metadata-Version: 2.4
Name: pkgstats
Version: 0.1.0
Summary: Tool to get the package statistics from a debian mirror.
Author-email: Alessandro Zanni <alessandrozanni.dev@gmail.com>
License-Expression: MIT
Project-URL: Homepage, https://github.com/echo-alez/pkgstats
Project-URL: Issues, https://github.com/echo-alez/pkgstats/issues
Classifier: Programming Language :: Python :: 3
Classifier: Operating System :: OS Independent
Classifier: Topic :: System :: Archiving :: Packaging
Requires-Python: >=3.6
